discordextension/__init__.py
discordextension/messages.py
discordextension-1.0.4.dist-info/METADATA
discordextension-1.0.4.dist-info/WHEEL
discordextension-1.0.4.dist-info/top_level.txt
discordextension-1.0.4.dist-info/RECORD
