Metadata-Version: 2.1
Name: discordextension
Version: 1.0.4
Summary: Little discord.py extension
Home-page: UNKNOWN
Author: Feluxerich
Author-email: UNKNOWN
License: UNKNOWN
Platform: UNKNOWN
